odoo/addons/ssi_payroll_agreement/README.rst
odoo/addons/ssi_payroll_agreement/__init__.py
odoo/addons/ssi_payroll_agreement/__manifest__.py
odoo/addons/ssi_payroll_agreement/hooks.py
odoo/addons/ssi_payroll_agreement/menu.xml
odoo/addons/ssi_payroll_agreement/data/approval_template_data.xml
odoo/addons/ssi_payroll_agreement/data/ir_sequence_data.xml
odoo/addons/ssi_payroll_agreement/data/policy_template_data.xml
odoo/addons/ssi_payroll_agreement/data/sequence_template_data.xml
odoo/addons/ssi_payroll_agreement/models/__init__.py
odoo/addons/ssi_payroll_agreement/models/hr_employee.py
odoo/addons/ssi_payroll_agreement/models/hr_payslip.py
odoo/addons/ssi_payroll_agreement/models/hr_payslip_batch.py
odoo/addons/ssi_payroll_agreement/models/hr_salary_rule.py
odoo/addons/ssi_payroll_agreement/models/payroll_agreement.py
odoo/addons/ssi_payroll_agreement/models/payroll_agreement_input.py
odoo/addons/ssi_payroll_agreement/models/payroll_agreement_input_type.py
odoo/addons/ssi_payroll_agreement/models/payroll_agreement_type.py
odoo/addons/ssi_payroll_agreement/security/ir.model.access.csv
odoo/addons/ssi_payroll_agreement/security/ir_module_category_data.xml
odoo/addons/ssi_payroll_agreement/security/ir_rule_data.xml
odoo/addons/ssi_payroll_agreement/security/res_group_data.xml
odoo/addons/ssi_payroll_agreement/static/description/icon.png
odoo/addons/ssi_payroll_agreement/views/hr_employee_views.xml
odoo/addons/ssi_payroll_agreement/views/hr_payslip_views.xml
odoo/addons/ssi_payroll_agreement/views/payroll_agreement_input_type_views.xml
odoo/addons/ssi_payroll_agreement/views/payroll_agreement_input_views.xml
odoo/addons/ssi_payroll_agreement/views/payroll_agreement_type_views.xml
odoo/addons/ssi_payroll_agreement/views/payroll_agreement_views.xml
odoo14_addon_ssi_payroll_agreement-14.0.1.2.0.dist-info/METADATA
odoo14_addon_ssi_payroll_agreement-14.0.1.2.0.dist-info/WHEEL
odoo14_addon_ssi_payroll_agreement-14.0.1.2.0.dist-info/top_level.txt
odoo14_addon_ssi_payroll_agreement-14.0.1.2.0.dist-info/RECORD
